{
    "canvasURL": "https://jicanvas.com",
    "token": "cuDdhSH2aIbs9oAEfM7WdwFPiI1hHv1OnYSWapKtuqEEyQuMdmGyg2GkuK87N5ju",
    "courseCodes": [],
    "courseIDs": [
        349,
        177,
        333,
        406,
        411,
        186,
        124,
        112,
        108,
        26,
        91,
        90,
        150,
        156
    ],
    "downloadDir": "/home/wznmickey/fromCanvas",
    "filesizeThresh": 250.0,
    "allowAudio": true,
    "allowVideo": true,
    "allowImage": true
}